jtlib/__init__.py
jtlib/analytics_utils.py
jtlib/date_utils.py
jtlib/emailer.py
jtlib/excel_utils.py
jtlib/file_utils.py
jtlib/pd_utils.py
jtlib/sas_utils.py
jtlib-0.1.5.dist-info/METADATA
jtlib-0.1.5.dist-info/WHEEL
jtlib-0.1.5.dist-info/top_level.txt
jtlib-0.1.5.dist-info/RECORD
