Metadata-Version: 2.1
Name: jtlib
Version: 0.1.5
Summary: Utility library
Home-page: https://github.com/joeyturczak/jtlib
Author: Joey Turczak
Author-email: joeyturczak@gmail.com
License: MIT
Requires-Dist: pandas
